ddg_mcp/__init__.py
ddg_mcp/server.py
ddg_mcp-0.1.1.dist-info/METADATA
ddg_mcp-0.1.1.dist-info/WHEEL
ddg_mcp-0.1.1.dist-info/entry_points.txt
ddg_mcp-0.1.1.dist-info/RECORD
