Metadata-Version: 2.4
Name: ddg-mcp
Version: 0.1.1
Summary: DuckDuckGo search API MCP
Author-email: Shannon Sands <shannon.sands.1979@gmail.com>
Requires-Python: >=3.11
Requires-Dist: duckduckgo-search>=7.5.1
Requires-Dist: mcp>=1.3.0
